bin/importconverterdict
bin/unitconvertertest
whyis_unit_converter/__init__.py
whyis_unit_converter/attr_converter.py
whyis_unit_converter/convert.py
whyis_unit_converter/convert_values.py
whyis_unit_converter/converter.py
whyis_unit_converter/dictionary.py
whyis_unit_converter/kg_parser.py
whyis_unit_converter/read_dictionary.py
whyis_unit_converter/test_Unit_Converter.py
whyis_unit_converter/unit_converter.py
whyis_unit_converter/unit_converter_agent.py
whyis_unit_converter/dicts/nanomine_dictionary.txt
whyis_unit_converter/dicts/translations.txt
whyis_unit_converter-0.0.2.data/scripts/importconverterdict
whyis_unit_converter-0.0.2.data/scripts/unitconvertertest
whyis_unit_converter-0.0.2.dist-info/LICENSE
whyis_unit_converter-0.0.2.dist-info/METADATA
whyis_unit_converter-0.0.2.dist-info/WHEEL
whyis_unit_converter-0.0.2.dist-info/top_level.txt
whyis_unit_converter-0.0.2.dist-info/RECORD
