Metadata-Version: 2.1
Name: whyis-unit-converter
Version: 0.0.2
Summary: Unit converter for Whyis
Home-page: https://github.com/roryschadler/whyis_unit_converter
Author: Rory Schadler
Author-email: rory.h.schadler.21@dartmouth.edu
License: UNKNOWN
Platform: UNKNOWN
Classifier: Programming Language :: Python :: 3
Classifier: License :: OSI Approved :: MIT License
Classifier: Operating System :: OS Independent
Requires-Python: >=3.5.2
Requires-Dist: Pint
Requires-Dist: rdflib
